trackrip/__init__.py
trackrip/__main__.py
trackrip/pcm.py
trackrip/tracker.py
trackrip-1.2.2.dist-info/LICENSE.txt
trackrip-1.2.2.dist-info/METADATA
trackrip-1.2.2.dist-info/WHEEL
trackrip-1.2.2.dist-info/entry_points.txt
trackrip-1.2.2.dist-info/top_level.txt
trackrip-1.2.2.dist-info/RECORD
