Metadata-Version: 2.1
Name: trackrip
Version: 1.2.2
Summary: Extracts samples from various music tracker module formats
Home-page: https://github.com/dbrookman/trackrip
Author: Daniel Brookman
Author-email: dannntrax@gmail.com
License: MIT
Keywords: tracker music samples mod s3m it umx
Platform: UNKNOWN
Classifier: Development Status :: 4 - Beta
Classifier: Environment :: Console
Classifier: Intended Audience :: End Users/Desktop
Classifier: License :: OSI Approved :: MIT License
Classifier: Programming Language :: Python :: 3.7
Classifier: Programming Language :: Python :: 3.8
Classifier: Programming Language :: Python :: 3.9
Classifier: Topic :: Multimedia :: Sound/Audio
Classifier: Topic :: Multimedia :: Sound/Audio :: Conversion
Classifier: Topic :: Terminals
Classifier: Topic :: Utilities
Requires-Python: >=3.7
License-File: LICENSE.txt
